setup.cfg
setup.py
fast_dbscan/__init__.py
fast_dbscan/fast_dbscan.py
fast_dbscan.egg-info/PKG-INFO
fast_dbscan.egg-info/SOURCES.txt
fast_dbscan.egg-info/dependency_links.txt
fast_dbscan.egg-info/entry_points.txt
fast_dbscan.egg-info/not-zip-safe
fast_dbscan.egg-info/requires.txt
fast_dbscan.egg-info/top_level.txt
src/dbscan.c
src/dbscan_module.pyx