Metadata-Version: 1.1
Name: fast-dbscan
Version: 0.1.0
Summary: fast dbscan clustering on peptide strings
Home-page: https://github.com/harmslab/fast_dbscan
Author: Michael J. Harms
Author-email: harmsm@gmail.com
License: UNKNOWN
Download-URL: https://github.com/harmslab/fast_dbscan/archive/0.1.0.tar.gz
Platform: UNKNOWN
Classifier: Programming Language :: Python
